birdgame/__init__.py
birdgame/constants.py
birdgame/animation/__init__.py
birdgame/animation/animatebirds.py
birdgame/config/__init__.py
birdgame/config/getredisconfig.py
birdgame/config/certificates/__init__.py
birdgame/config/certificates/ca.crt
birdgame/datasources/__init__.py
birdgame/datasources/livedata.py
birdgame/datasources/remotetestdata.py
birdgame/examples/__init__.py
birdgame/examples/derived/__init__.py
birdgame/examples/derived/autoetstracker.py
birdgame/examples/derived/ewmatracker.py
birdgame/examples/derived/gmmtracker.py
birdgame/examples/derived/mixturetracker.py
birdgame/examples/derived/ngboosttracker.py
birdgame/examples/derived/quantileregtracker.py
birdgame/examples/derived/torchgmmtracker.py
birdgame/examples/derived/volscaledgmmtracker.py
birdgame/examples/selfcontained/__init__.py
birdgame/examples/selfcontained/selfcontainedmixturetrackerexample.py
birdgame/model_benchmark/__init__.py
birdgame/model_benchmark/emwavartracker.py
birdgame/stats/__init__.py
birdgame/stats/fewmean.py
birdgame/stats/fewmeans.py
birdgame/stats/fewmedian.py
birdgame/stats/fewvar.py
birdgame/stats/jumpdiffusion.py
birdgame/stats/tanhmean.py
birdgame/trackers/__init__.py
birdgame/trackers/tracker_evaluator.py
birdgame/trackers/trackerbase.py
birdgame/visualization/__init__.py
birdgame/visualization/animated_viz_predictions.py
birdgame/visualization/animator.py
birdgame/visualization/utils.py
birdgame/visualization/viz_autoets.py
birdgame/visualization/viz_fewvar.py
birdgame/visualization/viz_ngboost.py
birdgame/visualization/viz_predictions.py
birdgame/visualization/viz_quantile_regression.py
birdgame/wealth/__init__.py
birdgame/wealth/wealth_mechanism.py
birdgame-0.3.1.dist-info/licenses/LICENSE
birdgame-0.3.1.dist-info/METADATA
birdgame-0.3.1.dist-info/WHEEL
birdgame-0.3.1.dist-info/entry_points.txt
birdgame-0.3.1.dist-info/top_level.txt
birdgame-0.3.1.dist-info/RECORD
