Metadata-Version: 2.4
Name: birdgame
Version: 0.3.1
Summary: Utilities to help play the Bird Game at crunchdao.com
Home-page: https://github.com/microprediction/birdgame
Author: microprediction
Author-email: peter.cotton@microprediction.com
License: MIT
Classifier: License :: OSI Approved :: MIT License
Classifier: Programming Language :: Python :: 3
Classifier: Programming Language :: Python :: 3.12
License-File: LICENSE
Requires-Dist: pandas
Requires-Dist: river
Requires-Dist: density
Requires-Dist: densitypdf>=0.1.4
Requires-Dist: matplotlib
Requires-Dist: redis
Requires-Dist: orjson
Requires-Dist: tqdm
Requires-Dist: numpy
Requires-Dist: IPython
Dynamic: author
Dynamic: author-email
Dynamic: classifier
Dynamic: description
Dynamic: description-content-type
Dynamic: home-page
Dynamic: license
Dynamic: license-file
Dynamic: requires-dist
Dynamic: summary
